weather_reporter/cli.py
weather_reporter/utils.py
weather629-1.0.1.dist-info/LICENSE
weather629-1.0.1.dist-info/METADATA
weather629-1.0.1.dist-info/WHEEL
weather629-1.0.1.dist-info/entry_points.txt
weather629-1.0.1.dist-info/top_level.txt
weather629-1.0.1.dist-info/RECORD
