Metadata-Version: 2.1
Name: weather629
Version: 1.0.1
Summary: A Python package to get weather reports for any location.
Home-page: https://github.com/nikhilkumarsingh/weather-reporter
Author: XiaoyanLi
Author-email: xiaoyanli629@gmail.com
License: MIT
Platform: UNKNOWN
Classifier: License :: OSI Approved :: MIT License
Classifier: Programming Language :: Python :: 3
Classifier: Programming Language :: Python :: 3.7
Requires-Dist: requests
